miracron/__init__.py
miracron/miracron.py
miracron-0.4.1.dist-info/LICENSE
miracron-0.4.1.dist-info/METADATA
miracron-0.4.1.dist-info/WHEEL
miracron-0.4.1.dist-info/entry_points.txt
miracron-0.4.1.dist-info/top_level.txt
miracron-0.4.1.dist-info/RECORD
