Metadata-Version: 2.1
Name: miracron
Version: 0.4.1
Summary: A cron rule generator for scheduled TV recording with mirakc/Mirakurun
Author: maeda577
Maintainer: maeda577
License: Unlicense
Project-URL: Repository, https://github.com/maeda577/miracron
Keywords: DTV
Classifier: Development Status :: 4 - Beta
Classifier: Environment :: Console
Classifier: License :: OSI Approved :: The Unlicense (Unlicense)
Classifier: Programming Language :: Python :: 3
Requires-Python: >=3.9
License-File: LICENSE
Requires-Dist: pyyaml
Requires-Dist: pydantic
